rayroom/__init__.py
rayroom/analytics/acoustics.py
rayroom/analytics/performance.py
rayroom/core/__init__.py
rayroom/core/constants.py
rayroom/core/geometry.py
rayroom/core/physics.py
rayroom/core/utils.py
rayroom/effects/__init__.py
rayroom/effects/presets.py
rayroom/engines/__init__.py
rayroom/engines/dgfem/__init__.py
rayroom/engines/dgfem/dgfem.py
rayroom/engines/hybrid/hybrid.py
rayroom/engines/hybrid_dgfem/__init__.py
rayroom/engines/hybrid_dgfem/hybrid_dgfem.py
rayroom/engines/ism/__init__.py
rayroom/engines/ism/ism.py
rayroom/engines/radiosity/__init__.py
rayroom/engines/radiosity/core.py
rayroom/engines/radiosity/radiosity.py
rayroom/engines/raytracer/__init__.py
rayroom/engines/raytracer/audio.py
rayroom/engines/raytracer/core.py
rayroom/engines/spectral/__init__.py
rayroom/engines/spectral/fdtd.py
rayroom/engines/spectral/spectral.py
rayroom/room/__init__.py
rayroom/room/base.py
rayroom/room/materials.py
rayroom/room/objects.py
rayroom/room/visualize.py
rayroom/room/database/__init__.py
rayroom/room/database/base.py
rayroom/room/database/demo.py
rayroom/room/database/test_bench.py
rayroom/room/database/medical/__init__.py
rayroom/room/database/medical/base.py
rayroom/room/database/medical/room_12m.py
rayroom/room/database/medical/room_15m.py
rayroom/room/database/medical/room_16m_consulting.py
rayroom/room/database/medical/room_16m_examination.py
rayroom/room/database/medical/room_18m.py
rayroom/room/database/medical/room_20m.py
rayroom/room/database/medical/room_24m.py
rayroom/room/database/medical/room_32m.py
rayroom/room/database/medical/room_4_5m.py
rayroom/room/database/medical/room_6m.py
rayroom/room/database/medical/room_8m.py
rayroom/room/database/medical/room_9_5m.py
rayroom/room/templates/room_creator_template.html
rayroom/room/templates/viewer_index_template.html
rayroom/room/templates/viewer_template.html
rayroom-0.4.1.dist-info/licenses/LICENSE
rayroom-0.4.1.dist-info/METADATA
rayroom-0.4.1.dist-info/WHEEL
rayroom-0.4.1.dist-info/top_level.txt
rayroom-0.4.1.dist-info/RECORD
