Metadata-Version: 2.4
Name: rayroom
Version: 0.4.1
Summary: A Python-based ray tracing acoustics simulator supporting complex room geometries, materials, and furniture.
Author: Yanis Labrak
License-Expression: MIT
Project-URL: Homepage, https://github.com/rayroom/rayroom
Project-URL: Bug Tracker, https://github.com/rayroom/rayroom/issues
Classifier: Programming Language :: Python :: 3
Classifier: Operating System :: OS Independent
Classifier: Topic :: Scientific/Engineering :: Physics
Classifier: Topic :: Multimedia :: Sound/Audio
Requires-Python: >=3.8
License-File: LICENSE
Requires-Dist: numpy
Requires-Dist: scipy
Requires-Dist: matplotlib
Requires-Dist: tqdm
Requires-Dist: mosqito
Requires-Dist: jinja2
Provides-Extra: docs
Requires-Dist: sphinx; extra == "docs"
Requires-Dist: sphinx-rtd-theme; extra == "docs"
Dynamic: license-file
